MANIFEST.in
README.md
setup.cfg
setup.py
pyxmex/__init__.py
pyxmex/cbnot_parser.py
pyxmex/eptrn_parser.py
pyxmex/joiner.py
pyxmex/parser.py
pyxmex/type_caster.py
pyxmex/utils.py
pyxmex.egg-info/PKG-INFO
pyxmex.egg-info/SOURCES.txt
pyxmex.egg-info/dependency_links.txt
pyxmex.egg-info/not-zip-safe
pyxmex.egg-info/requires.txt
pyxmex.egg-info/top_level.txt
pyxmex/config/cbnot.yml
pyxmex/config/eptrn.yml