Metadata-Version: 1.1
Name: pyxmex
Version: 0.3.0
Summary: Parse American Express EPTRN and CBNOT files
Home-page: https://github.com/lumoslabs/pyxmex
Author: Rob Froetscher, Joyce Lau
Author-email: rfroetscher@lumoslabs.com
License: MIT
Download-URL: https://github.com/lumoslabs/pyxmex/tarball/0.3.0
Platform: UNKNOWN
